py_expect/__init__.py
py_expect-0.1.2.dist-info/DESCRIPTION.rst
py_expect-0.1.2.dist-info/METADATA
py_expect-0.1.2.dist-info/RECORD
py_expect-0.1.2.dist-info/WHEEL
py_expect-0.1.2.dist-info/metadata.json
py_expect-0.1.2.dist-info/top_level.txt
