Metadata-Version: 2.0
Name: py-expect
Version: 0.1.2
Summary: Python validate tool for json or other else
Home-page: https://github.com/mrhack/py-expect
Author: mrhack
Author-email: hdg1988@gmail.com
License: UNKNOWN
Keywords: python json data validate
Platform: all
Classifier: Development Status :: 4 - Beta
Classifier: Operating System :: OS Independent
Classifier: Intended Audience :: Developers
Classifier: License :: OSI Approved :: MIT License
Classifier: Programming Language :: Python
Classifier: Programming Language :: Python :: Implementation
Classifier: Programming Language :: Python :: 2
Classifier: Programming Language :: Python :: 2.7
Classifier: Programming Language :: Python :: 3
Classifier: Programming Language :: Python :: 3.4
Classifier: Programming Language :: Python :: 3.5
Classifier: Programming Language :: Python :: 3.6
Classifier: Topic :: Software Development :: Libraries
